DESIGN.md
LICENSE.md
MANIFEST.in
README.rst
STYLE.md
setup.py
test-requirements.txt
staffeli/assignment.py
staffeli/cachable.py
staffeli/canvas.py
staffeli/canvasTA-subs.py
staffeli/cli.py
staffeli/course.py
staffeli/files.py
staffeli/listed.py
staffeli/names.py
staffeli/resubmissions.py
staffeli/speedgrader_url.py
staffeli/submission.py
staffeli/typed_canvas.py
staffeli/upload.py
staffeli.egg-info/PKG-INFO
staffeli.egg-info/SOURCES.txt
staffeli.egg-info/dependency_links.txt
staffeli.egg-info/entry_points.txt
staffeli.egg-info/requires.txt
staffeli.egg-info/top_level.txt