Metadata-Version: 1.0
Name: staffeli
Version: 0.4.2
Summary: DIKU support tools for Canvas LMS
Home-page: https://github.com/DIKU-EDU/staffeli
Author: Oleks
Author-email: oleks@oleks.info
License: EUPLv1.1
Keywords: staffeli,Canvas,DIKU
Platform: UNKNOWN
